Metadata-Version: 2.0
Name: odoo10-addon-purchase-open-qty
Version: 10.0.1.1.0
Summary: Allows to identify the purchase orders that have quantities pending to invoice or to receive.
Home-page: https://github.com/OCA/purchase-workflow
Author: Eficent, Odoo Community Association (OCA)
Author-email: support@odoo-community.org
License: AGPL-3
Platform: UNKNOWN
Classifier: Programming Language :: Python
Classifier: Framework :: Odoo
Classifier: License :: OSI Approved :: GNU Affero General Public License v3
Requires-Python: ~=2.7
Requires-Dist: odoo (<10.1dev,>=10.0)
